ripedb/__init__.py
ripedb/main.py
ripedb/utils/__init__.py
ripedb/utils/expand_ip_range.py
ripedb/utils/export_data_to_xlsx.py
ripedb/utils/export_xlsx.py
ripedb/utils/export_xlsx_new_sheet.py
ripedb/utils/get_export_path.py
ripedb/utils/get_ripe_reverse_dns.py
ripedb/utils/helper.py
ripedb/utils/process_input_indixes.py
ripedb/utils/range_to_cidr.py
ripedb/utils/remove_lines.py
ripedb/utils/remove_rows.py
ripedb/utils/request_and_validate_indices.py
ripedb/utils/request_confirm.py
ripedb/utils/reverse_dns.py
RipeDB-0.4.0.dist-info/LICENSE
RipeDB-0.4.0.dist-info/METADATA
RipeDB-0.4.0.dist-info/WHEEL
RipeDB-0.4.0.dist-info/entry_points.txt
RipeDB-0.4.0.dist-info/top_level.txt
RipeDB-0.4.0.dist-info/RECORD
