Metadata-Version: 2.1
Name: RipeDB
Version: 0.4.0
Summary: A tool for making analyssis on RipeDB
Home-page: https://github.com/apt-0/RipeDB
Author: APT-0-Blog
Author-email: cryptovortex@outlook.com
Keywords: ripe ripedb
License-File: LICENSE
Requires-Dist: requests
Requires-Dist: pandas
Requires-Dist: openpyxl
